COPYING
MANIFEST.in
README
changelog
setup.cfg
setup.py
bdsync_manager/__init__.py
bdsync_manager/cmdline.py
bdsync_manager/config.py
bdsync_manager/lvm.py
bdsync_manager/task.py
bdsync_manager/utils.py
bdsync_manager.egg-info/PKG-INFO
bdsync_manager.egg-info/SOURCES.txt
bdsync_manager.egg-info/dependency_links.txt
bdsync_manager.egg-info/entry_points.txt
bdsync_manager.egg-info/requires.txt
bdsync_manager.egg-info/top_level.txt