Metadata-Version: 1.1
Name: bdsync-manager
Version: 0.3.0
Summary: Synchronize one or more blockdevices to a remote target via bdsync
Home-page: http://www.nongnu.org/bdsync-manager/
Author: Lars Kruse
Author-email: devel@sumpfralle.de
License: UNKNOWN
Platform: UNKNOWN
Classifier: Development Status :: 3 - Alpha
Classifier: Programming Language :: Python :: 3
Classifier: Environment :: Console
Classifier: Intended Audience :: System Administrators
Classifier: License :: OSI Approved :: GNU General Public License v3 or later (GPLv3+)
Classifier: Natural Language :: English
Classifier: Topic :: System :: Archiving :: Backup
Classifier: Topic :: Utilities
